{"hits":{"total":{"value":3803,"relation":"eq"},"max_score":19.612666999999998,"hits":[{"_source":{"documentId":"e3ccd5b7","chunkIndex":0,"totalChunks":1,"charStart":0,"charEnd":31,"chunkSize":31,"isChunked":false,"startPage":1,"endPage":1,"ORIGIN_FILE_NAME":"EFTA00128591.pdf","ORIGIN_FILE_URI":"https:\/\/www.justice.gov\/epstein\/files\/DataSet 9\/EFTA00128591.pdf","bucket":"amazon-s3x-sync","key":"DataSet 9\/EFTA00128591.pdf","contentType":"application\/pdf","fileSize":2433,"totalWords":4,"totalCharacters":31,"processedAt":"2026-01-30T16:28:19Z","indexedAt":"2026-01-30T16:28:19Z","source":"document-indexing-pipeline"},"fields":{"ORIGIN_FILE_NAME":["EFTA00128591.pdf"]},"highlight":{"content":["\u003Cem\u003ENo\u003C\/em\u003E \u003Cem\u003EImages\u003C\/em\u003E \u003Cem\u003EProduced\u003C\/em\u003E\nEFTA00128591"]}},{"_source":{"documentId":"6b0468b9","chunkIndex":0,"totalChunks":1,"charStart":0,"charEnd":31,"chunkSize":31,"isChunked":false,"startPage":1,"endPage":1,"ORIGIN_FILE_NAME":"EFTA00128596.pdf","ORIGIN_FILE_URI":"https:\/\/www.justice.gov\/epstein\/files\/DataSet 9\/EFTA00128596.pdf","bucket":"amazon-s3x-sync","key":"DataSet 9\/EFTA00128596.pdf","contentType":"application\/pdf","fileSize":2433,"totalWords":4,"totalCharacters":31,"processedAt":"2026-01-30T16:28:19Z","indexedAt":"2026-01-30T16:28:19Z","source":"document-indexing-pipeline"},"fields":{"ORIGIN_FILE_NAME":["EFTA00128596.pdf"]},"highlight":{"content":["\u003Cem\u003ENo\u003C\/em\u003E \u003Cem\u003EImages\u003C\/em\u003E \u003Cem\u003EProduced\u003C\/em\u003E\nEFTA00128596"]}},{"_source":{"documentId":"7c47a359","chunkIndex":0,"totalChunks":1,"charStart":0,"charEnd":31,"chunkSize":31,"isChunked":false,"startPage":1,"endPage":1,"ORIGIN_FILE_NAME":"EFTA00128582.pdf","ORIGIN_FILE_URI":"https:\/\/www.justice.gov\/epstein\/files\/DataSet 9\/EFTA00128582.pdf","bucket":"amazon-s3x-sync","key":"DataSet 9\/EFTA00128582.pdf","contentType":"application\/pdf","fileSize":2433,"totalWords":4,"totalCharacters":31,"processedAt":"2026-01-30T16:28:20Z","indexedAt":"2026-01-30T16:28:20Z","source":"document-indexing-pipeline"},"fields":{"ORIGIN_FILE_NAME":["EFTA00128582.pdf"]},"highlight":{"content":["\u003Cem\u003ENo\u003C\/em\u003E \u003Cem\u003EImages\u003C\/em\u003E \u003Cem\u003EProduced\u003C\/em\u003E\nEFTA00128582"]}},{"_source":{"documentId":"33013c36","chunkIndex":0,"totalChunks":1,"charStart":0,"charEnd":31,"chunkSize":31,"isChunked":false,"startPage":1,"endPage":1,"ORIGIN_FILE_NAME":"EFTA00128558.pdf","ORIGIN_FILE_URI":"https:\/\/www.justice.gov\/epstein\/files\/DataSet 9\/EFTA00128558.pdf","bucket":"amazon-s3x-sync","key":"DataSet 9\/EFTA00128558.pdf","contentType":"application\/pdf","fileSize":2433,"totalWords":4,"totalCharacters":31,"processedAt":"2026-01-30T16:28:22Z","indexedAt":"2026-01-30T16:28:22Z","source":"document-indexing-pipeline"},"fields":{"ORIGIN_FILE_NAME":["EFTA00128558.pdf"]},"highlight":{"content":["\u003Cem\u003ENo\u003C\/em\u003E \u003Cem\u003EImages\u003C\/em\u003E \u003Cem\u003EProduced\u003C\/em\u003E\nEFTA00128558"]}},{"_source":{"documentId":"9e960a8e","chunkIndex":0,"totalChunks":1,"charStart":0,"charEnd":31,"chunkSize":31,"isChunked":false,"startPage":1,"endPage":1,"ORIGIN_FILE_NAME":"EFTA00128624.pdf","ORIGIN_FILE_URI":"https:\/\/www.justice.gov\/epstein\/files\/DataSet 9\/EFTA00128624.pdf","bucket":"amazon-s3x-sync","key":"DataSet 9\/EFTA00128624.pdf","contentType":"application\/pdf","fileSize":2433,"totalWords":4,"totalCharacters":31,"processedAt":"2026-01-30T16:28:22Z","indexedAt":"2026-01-30T16:28:22Z","source":"document-indexing-pipeline"},"fields":{"ORIGIN_FILE_NAME":["EFTA00128624.pdf"]},"highlight":{"content":["\u003Cem\u003ENo\u003C\/em\u003E \u003Cem\u003EImages\u003C\/em\u003E \u003Cem\u003EProduced\u003C\/em\u003E\nEFTA00128624"]}},{"_source":{"documentId":"c97a959b","chunkIndex":0,"totalChunks":1,"charStart":0,"charEnd":31,"chunkSize":31,"isChunked":false,"startPage":1,"endPage":1,"ORIGIN_FILE_NAME":"EFTA00128622.pdf","ORIGIN_FILE_URI":"https:\/\/www.justice.gov\/epstein\/files\/DataSet 9\/EFTA00128622.pdf","bucket":"amazon-s3x-sync","key":"DataSet 9\/EFTA00128622.pdf","contentType":"application\/pdf","fileSize":2433,"totalWords":4,"totalCharacters":31,"processedAt":"2026-01-30T16:28:23Z","indexedAt":"2026-01-30T16:28:23Z","source":"document-indexing-pipeline"},"fields":{"ORIGIN_FILE_NAME":["EFTA00128622.pdf"]},"highlight":{"content":["\u003Cem\u003ENo\u003C\/em\u003E \u003Cem\u003EImages\u003C\/em\u003E \u003Cem\u003EProduced\u003C\/em\u003E\nEFTA00128622"]}},{"_source":{"documentId":"82932037","chunkIndex":0,"totalChunks":1,"charStart":0,"charEnd":31,"chunkSize":31,"isChunked":false,"startPage":1,"endPage":1,"ORIGIN_FILE_NAME":"EFTA00128473.pdf","ORIGIN_FILE_URI":"https:\/\/www.justice.gov\/epstein\/files\/DataSet 9\/EFTA00128473.pdf","bucket":"amazon-s3x-sync","key":"DataSet 9\/EFTA00128473.pdf","contentType":"application\/pdf","fileSize":2433,"totalWords":4,"totalCharacters":31,"processedAt":"2026-01-30T16:28:27Z","indexedAt":"2026-01-30T16:28:27Z","source":"document-indexing-pipeline"},"fields":{"ORIGIN_FILE_NAME":["EFTA00128473.pdf"]},"highlight":{"content":["\u003Cem\u003ENo\u003C\/em\u003E \u003Cem\u003EImages\u003C\/em\u003E \u003Cem\u003EProduced\u003C\/em\u003E\nEFTA00128473"]}},{"_source":{"documentId":"7831ce9e","chunkIndex":0,"totalChunks":1,"charStart":0,"charEnd":31,"chunkSize":31,"isChunked":false,"startPage":1,"endPage":1,"ORIGIN_FILE_NAME":"EFTA00128465.pdf","ORIGIN_FILE_URI":"https:\/\/www.justice.gov\/epstein\/files\/DataSet 9\/EFTA00128465.pdf","bucket":"amazon-s3x-sync","key":"DataSet 9\/EFTA00128465.pdf","contentType":"application\/pdf","fileSize":2433,"totalWords":4,"totalCharacters":31,"processedAt":"2026-01-30T16:28:35Z","indexedAt":"2026-01-30T16:28:35Z","source":"document-indexing-pipeline"},"fields":{"ORIGIN_FILE_NAME":["EFTA00128465.pdf"]},"highlight":{"content":["\u003Cem\u003ENo\u003C\/em\u003E \u003Cem\u003EImages\u003C\/em\u003E \u003Cem\u003EProduced\u003C\/em\u003E\nEFTA00128465"]}},{"_source":{"documentId":"d4451b9c","chunkIndex":0,"totalChunks":1,"charStart":0,"charEnd":31,"chunkSize":31,"isChunked":false,"startPage":1,"endPage":1,"ORIGIN_FILE_NAME":"EFTA00128469.pdf","ORIGIN_FILE_URI":"https:\/\/www.justice.gov\/epstein\/files\/DataSet 9\/EFTA00128469.pdf","bucket":"amazon-s3x-sync","key":"DataSet 9\/EFTA00128469.pdf","contentType":"application\/pdf","fileSize":2433,"totalWords":4,"totalCharacters":31,"processedAt":"2026-01-30T16:28:36Z","indexedAt":"2026-01-30T16:28:36Z","source":"document-indexing-pipeline"},"fields":{"ORIGIN_FILE_NAME":["EFTA00128469.pdf"]},"highlight":{"content":["\u003Cem\u003ENo\u003C\/em\u003E \u003Cem\u003EImages\u003C\/em\u003E \u003Cem\u003EProduced\u003C\/em\u003E\nEFTA00128469"]}},{"_source":{"documentId":"32f41c3d","chunkIndex":0,"totalChunks":1,"charStart":0,"charEnd":31,"chunkSize":31,"isChunked":false,"startPage":1,"endPage":1,"ORIGIN_FILE_NAME":"EFTA00128512.pdf","ORIGIN_FILE_URI":"https:\/\/www.justice.gov\/epstein\/files\/DataSet 9\/EFTA00128512.pdf","bucket":"amazon-s3x-sync","key":"DataSet 9\/EFTA00128512.pdf","contentType":"application\/pdf","fileSize":2433,"totalWords":4,"totalCharacters":31,"processedAt":"2026-01-30T16:28:36Z","indexedAt":"2026-01-30T16:28:36Z","source":"document-indexing-pipeline"},"fields":{"ORIGIN_FILE_NAME":["EFTA00128512.pdf"]},"highlight":{"content":["\u003Cem\u003ENo\u003C\/em\u003E \u003Cem\u003EImages\u003C\/em\u003E \u003Cem\u003EProduced\u003C\/em\u003E\nEFTA00128512"]}}]},"aggregations":{"unique_count":{"value":3803}}}