{"hits":{"total":{"value":3803,"relation":"eq"},"max_score":19.612666999999998,"hits":[{"_source":{"documentId":"7886a8e2","chunkIndex":0,"totalChunks":1,"charStart":0,"charEnd":31,"chunkSize":31,"isChunked":false,"startPage":1,"endPage":1,"ORIGIN_FILE_NAME":"EFTA00280584.pdf","ORIGIN_FILE_URI":"https:\/\/www.justice.gov\/epstein\/files\/DataSet 9\/EFTA00280584.pdf","bucket":"amazon-s3x-sync","key":"DataSet 9\/EFTA00280584.pdf","contentType":"application\/pdf","fileSize":2433,"totalWords":4,"totalCharacters":31,"processedAt":"2026-01-30T16:48:36Z","indexedAt":"2026-01-30T16:48:36Z","source":"document-indexing-pipeline"},"fields":{"ORIGIN_FILE_NAME":["EFTA00280584.pdf"]},"highlight":{"content":["\u003Cem\u003ENo\u003C\/em\u003E \u003Cem\u003EImages\u003C\/em\u003E \u003Cem\u003EProduced\u003C\/em\u003E\nEFTA00280584"]}},{"_source":{"documentId":"9a07b5ef","chunkIndex":0,"totalChunks":1,"charStart":0,"charEnd":31,"chunkSize":31,"isChunked":false,"startPage":1,"endPage":1,"ORIGIN_FILE_NAME":"EFTA00280054.pdf","ORIGIN_FILE_URI":"https:\/\/www.justice.gov\/epstein\/files\/DataSet 9\/EFTA00280054.pdf","bucket":"amazon-s3x-sync","key":"DataSet 9\/EFTA00280054.pdf","contentType":"application\/pdf","fileSize":2433,"totalWords":4,"totalCharacters":31,"processedAt":"2026-01-30T16:48:36Z","indexedAt":"2026-01-30T16:48:36Z","source":"document-indexing-pipeline"},"fields":{"ORIGIN_FILE_NAME":["EFTA00280054.pdf"]},"highlight":{"content":["\u003Cem\u003ENo\u003C\/em\u003E \u003Cem\u003EImages\u003C\/em\u003E \u003Cem\u003EProduced\u003C\/em\u003E\nEFTA00280054"]}},{"_source":{"documentId":"675426e6","chunkIndex":0,"totalChunks":1,"charStart":0,"charEnd":31,"chunkSize":31,"isChunked":false,"startPage":1,"endPage":1,"ORIGIN_FILE_NAME":"EFTA00280614.pdf","ORIGIN_FILE_URI":"https:\/\/www.justice.gov\/epstein\/files\/DataSet 9\/EFTA00280614.pdf","bucket":"amazon-s3x-sync","key":"DataSet 9\/EFTA00280614.pdf","contentType":"application\/pdf","fileSize":2433,"totalWords":4,"totalCharacters":31,"processedAt":"2026-01-30T16:48:36Z","indexedAt":"2026-01-30T16:48:36Z","source":"document-indexing-pipeline"},"fields":{"ORIGIN_FILE_NAME":["EFTA00280614.pdf"]},"highlight":{"content":["\u003Cem\u003ENo\u003C\/em\u003E \u003Cem\u003EImages\u003C\/em\u003E \u003Cem\u003EProduced\u003C\/em\u003E\nEFTA00280614"]}},{"_source":{"documentId":"381a0ea4","chunkIndex":0,"totalChunks":1,"charStart":0,"charEnd":31,"chunkSize":31,"isChunked":false,"startPage":1,"endPage":1,"ORIGIN_FILE_NAME":"EFTA00280573.pdf","ORIGIN_FILE_URI":"https:\/\/www.justice.gov\/epstein\/files\/DataSet 9\/EFTA00280573.pdf","bucket":"amazon-s3x-sync","key":"DataSet 9\/EFTA00280573.pdf","contentType":"application\/pdf","fileSize":2433,"totalWords":4,"totalCharacters":31,"processedAt":"2026-01-30T16:48:36Z","indexedAt":"2026-01-30T16:48:36Z","source":"document-indexing-pipeline"},"fields":{"ORIGIN_FILE_NAME":["EFTA00280573.pdf"]},"highlight":{"content":["\u003Cem\u003ENo\u003C\/em\u003E \u003Cem\u003EImages\u003C\/em\u003E \u003Cem\u003EProduced\u003C\/em\u003E\nEFTA00280573"]}},{"_source":{"documentId":"f16ca509","chunkIndex":0,"totalChunks":1,"charStart":0,"charEnd":31,"chunkSize":31,"isChunked":false,"startPage":1,"endPage":1,"ORIGIN_FILE_NAME":"EFTA00280591.pdf","ORIGIN_FILE_URI":"https:\/\/www.justice.gov\/epstein\/files\/DataSet 9\/EFTA00280591.pdf","bucket":"amazon-s3x-sync","key":"DataSet 9\/EFTA00280591.pdf","contentType":"application\/pdf","fileSize":2433,"totalWords":4,"totalCharacters":31,"processedAt":"2026-01-30T16:48:36Z","indexedAt":"2026-01-30T16:48:36Z","source":"document-indexing-pipeline"},"fields":{"ORIGIN_FILE_NAME":["EFTA00280591.pdf"]},"highlight":{"content":["\u003Cem\u003ENo\u003C\/em\u003E \u003Cem\u003EImages\u003C\/em\u003E \u003Cem\u003EProduced\u003C\/em\u003E\nEFTA00280591"]}},{"_source":{"documentId":"22620990","chunkIndex":0,"totalChunks":1,"charStart":0,"charEnd":31,"chunkSize":31,"isChunked":false,"startPage":1,"endPage":1,"ORIGIN_FILE_NAME":"EFTA00280610.pdf","ORIGIN_FILE_URI":"https:\/\/www.justice.gov\/epstein\/files\/DataSet 9\/EFTA00280610.pdf","bucket":"amazon-s3x-sync","key":"DataSet 9\/EFTA00280610.pdf","contentType":"application\/pdf","fileSize":2433,"totalWords":4,"totalCharacters":31,"processedAt":"2026-01-30T16:48:36Z","indexedAt":"2026-01-30T16:48:36Z","source":"document-indexing-pipeline"},"fields":{"ORIGIN_FILE_NAME":["EFTA00280610.pdf"]},"highlight":{"content":["\u003Cem\u003ENo\u003C\/em\u003E \u003Cem\u003EImages\u003C\/em\u003E \u003Cem\u003EProduced\u003C\/em\u003E\nEFTA00280610"]}},{"_source":{"documentId":"9ffbc824","chunkIndex":0,"totalChunks":1,"charStart":0,"charEnd":31,"chunkSize":31,"isChunked":false,"startPage":1,"endPage":1,"ORIGIN_FILE_NAME":"EFTA00280611.pdf","ORIGIN_FILE_URI":"https:\/\/www.justice.gov\/epstein\/files\/DataSet 9\/EFTA00280611.pdf","bucket":"amazon-s3x-sync","key":"DataSet 9\/EFTA00280611.pdf","contentType":"application\/pdf","fileSize":2433,"totalWords":4,"totalCharacters":31,"processedAt":"2026-01-30T16:48:36Z","indexedAt":"2026-01-30T16:48:36Z","source":"document-indexing-pipeline"},"fields":{"ORIGIN_FILE_NAME":["EFTA00280611.pdf"]},"highlight":{"content":["\u003Cem\u003ENo\u003C\/em\u003E \u003Cem\u003EImages\u003C\/em\u003E \u003Cem\u003EProduced\u003C\/em\u003E\nEFTA00280611"]}},{"_source":{"documentId":"bf52c598","chunkIndex":0,"totalChunks":1,"charStart":0,"charEnd":31,"chunkSize":31,"isChunked":false,"startPage":1,"endPage":1,"ORIGIN_FILE_NAME":"EFTA00280019.pdf","ORIGIN_FILE_URI":"https:\/\/www.justice.gov\/epstein\/files\/DataSet 9\/EFTA00280019.pdf","bucket":"amazon-s3x-sync","key":"DataSet 9\/EFTA00280019.pdf","contentType":"application\/pdf","fileSize":2433,"totalWords":4,"totalCharacters":31,"processedAt":"2026-01-30T16:48:36Z","indexedAt":"2026-01-30T16:48:36Z","source":"document-indexing-pipeline"},"fields":{"ORIGIN_FILE_NAME":["EFTA00280019.pdf"]},"highlight":{"content":["\u003Cem\u003ENo\u003C\/em\u003E \u003Cem\u003EImages\u003C\/em\u003E \u003Cem\u003EProduced\u003C\/em\u003E\nEFTA00280019"]}},{"_source":{"documentId":"df7bda92","chunkIndex":0,"totalChunks":1,"charStart":0,"charEnd":31,"chunkSize":31,"isChunked":false,"startPage":1,"endPage":1,"ORIGIN_FILE_NAME":"EFTA00280654.pdf","ORIGIN_FILE_URI":"https:\/\/www.justice.gov\/epstein\/files\/DataSet 9\/EFTA00280654.pdf","bucket":"amazon-s3x-sync","key":"DataSet 9\/EFTA00280654.pdf","contentType":"application\/pdf","fileSize":2433,"totalWords":4,"totalCharacters":31,"processedAt":"2026-01-30T16:48:36Z","indexedAt":"2026-01-30T16:48:36Z","source":"document-indexing-pipeline"},"fields":{"ORIGIN_FILE_NAME":["EFTA00280654.pdf"]},"highlight":{"content":["\u003Cem\u003ENo\u003C\/em\u003E \u003Cem\u003EImages\u003C\/em\u003E \u003Cem\u003EProduced\u003C\/em\u003E\nEFTA00280654"]}},{"_source":{"documentId":"86eae838","chunkIndex":0,"totalChunks":1,"charStart":0,"charEnd":31,"chunkSize":31,"isChunked":false,"startPage":1,"endPage":1,"ORIGIN_FILE_NAME":"EFTA00280671.pdf","ORIGIN_FILE_URI":"https:\/\/www.justice.gov\/epstein\/files\/DataSet 9\/EFTA00280671.pdf","bucket":"amazon-s3x-sync","key":"DataSet 9\/EFTA00280671.pdf","contentType":"application\/pdf","fileSize":2433,"totalWords":4,"totalCharacters":31,"processedAt":"2026-01-30T16:48:36Z","indexedAt":"2026-01-30T16:48:36Z","source":"document-indexing-pipeline"},"fields":{"ORIGIN_FILE_NAME":["EFTA00280671.pdf"]},"highlight":{"content":["\u003Cem\u003ENo\u003C\/em\u003E \u003Cem\u003EImages\u003C\/em\u003E \u003Cem\u003EProduced\u003C\/em\u003E\nEFTA00280671"]}}]},"aggregations":{"unique_count":{"value":3803}}}