{"hits":{"total":{"value":3803,"relation":"eq"},"max_score":19.597580000000001,"hits":[{"_source":{"documentId":"6b6a0323","chunkIndex":0,"totalChunks":1,"charStart":0,"charEnd":31,"chunkSize":31,"isChunked":false,"startPage":1,"endPage":1,"ORIGIN_FILE_NAME":"EFTA00033342.pdf","ORIGIN_FILE_URI":"https:\/\/www.justice.gov\/epstein\/files\/DataSet 8\/EFTA00033342.pdf","bucket":"amazon-s3x-sync","key":"DataSet 8\/EFTA00033342.pdf","contentType":"application\/pdf","fileSize":2433,"totalWords":4,"totalCharacters":31,"processedAt":"2026-01-21T01:39:25Z","indexedAt":"2026-01-21T01:39:25Z","source":"document-indexing-pipeline"},"fields":{"ORIGIN_FILE_NAME":["EFTA00033342.pdf"]},"highlight":{"content":["\u003Cem\u003ENo\u003C\/em\u003E \u003Cem\u003EImages\u003C\/em\u003E \u003Cem\u003EProduced\u003C\/em\u003E\nEFTA00033342"]}},{"_source":{"documentId":"fb251710","chunkIndex":0,"totalChunks":1,"charStart":0,"charEnd":31,"chunkSize":31,"isChunked":false,"startPage":1,"endPage":1,"ORIGIN_FILE_NAME":"EFTA00033039.pdf","ORIGIN_FILE_URI":"https:\/\/www.justice.gov\/epstein\/files\/DataSet 8\/EFTA00033039.pdf","bucket":"amazon-s3x-sync","key":"DataSet 8\/EFTA00033039.pdf","contentType":"application\/pdf","fileSize":2433,"totalWords":4,"totalCharacters":31,"processedAt":"2026-01-21T01:39:26Z","indexedAt":"2026-01-21T01:39:26Z","source":"document-indexing-pipeline"},"fields":{"ORIGIN_FILE_NAME":["EFTA00033039.pdf"]},"highlight":{"content":["\u003Cem\u003ENo\u003C\/em\u003E \u003Cem\u003EImages\u003C\/em\u003E \u003Cem\u003EProduced\u003C\/em\u003E\nEFTA00033039"]}},{"_source":{"documentId":"f1f51d6f","chunkIndex":0,"totalChunks":1,"charStart":0,"charEnd":31,"chunkSize":31,"isChunked":false,"startPage":1,"endPage":1,"ORIGIN_FILE_NAME":"EFTA00033166.pdf","ORIGIN_FILE_URI":"https:\/\/www.justice.gov\/epstein\/files\/DataSet 8\/EFTA00033166.pdf","bucket":"amazon-s3x-sync","key":"DataSet 8\/EFTA00033166.pdf","contentType":"application\/pdf","fileSize":2433,"totalWords":4,"totalCharacters":31,"processedAt":"2026-01-21T01:39:26Z","indexedAt":"2026-01-21T01:39:26Z","source":"document-indexing-pipeline"},"fields":{"ORIGIN_FILE_NAME":["EFTA00033166.pdf"]},"highlight":{"content":["\u003Cem\u003ENo\u003C\/em\u003E \u003Cem\u003EImages\u003C\/em\u003E \u003Cem\u003EProduced\u003C\/em\u003E\nEFTA00033166"]}},{"_source":{"documentId":"f19fb259","chunkIndex":0,"totalChunks":1,"charStart":0,"charEnd":31,"chunkSize":31,"isChunked":false,"startPage":1,"endPage":1,"ORIGIN_FILE_NAME":"EFTA00033121.pdf","ORIGIN_FILE_URI":"https:\/\/www.justice.gov\/epstein\/files\/DataSet 8\/EFTA00033121.pdf","bucket":"amazon-s3x-sync","key":"DataSet 8\/EFTA00033121.pdf","contentType":"application\/pdf","fileSize":2433,"totalWords":4,"totalCharacters":31,"processedAt":"2026-01-21T01:39:26Z","indexedAt":"2026-01-21T01:39:26Z","source":"document-indexing-pipeline"},"fields":{"ORIGIN_FILE_NAME":["EFTA00033121.pdf"]},"highlight":{"content":["\u003Cem\u003ENo\u003C\/em\u003E \u003Cem\u003EImages\u003C\/em\u003E \u003Cem\u003EProduced\u003C\/em\u003E\nEFTA00033121"]}},{"_source":{"documentId":"0e32439e","chunkIndex":0,"totalChunks":1,"charStart":0,"charEnd":31,"chunkSize":31,"isChunked":false,"startPage":1,"endPage":1,"ORIGIN_FILE_NAME":"EFTA00033207.pdf","ORIGIN_FILE_URI":"https:\/\/www.justice.gov\/epstein\/files\/DataSet 8\/EFTA00033207.pdf","bucket":"amazon-s3x-sync","key":"DataSet 8\/EFTA00033207.pdf","contentType":"application\/pdf","fileSize":2433,"totalWords":4,"totalCharacters":31,"processedAt":"2026-01-21T01:39:26Z","indexedAt":"2026-01-21T01:39:26Z","source":"document-indexing-pipeline"},"fields":{"ORIGIN_FILE_NAME":["EFTA00033207.pdf"]},"highlight":{"content":["\u003Cem\u003ENo\u003C\/em\u003E \u003Cem\u003EImages\u003C\/em\u003E \u003Cem\u003EProduced\u003C\/em\u003E\nEFTA00033207"]}},{"_source":{"documentId":"8f472aea","chunkIndex":0,"totalChunks":1,"charStart":0,"charEnd":31,"chunkSize":31,"isChunked":false,"startPage":1,"endPage":1,"ORIGIN_FILE_NAME":"EFTA00033209.pdf","ORIGIN_FILE_URI":"https:\/\/www.justice.gov\/epstein\/files\/DataSet 8\/EFTA00033209.pdf","bucket":"amazon-s3x-sync","key":"DataSet 8\/EFTA00033209.pdf","contentType":"application\/pdf","fileSize":2433,"totalWords":4,"totalCharacters":31,"processedAt":"2026-01-21T01:39:26Z","indexedAt":"2026-01-21T01:39:26Z","source":"document-indexing-pipeline"},"fields":{"ORIGIN_FILE_NAME":["EFTA00033209.pdf"]},"highlight":{"content":["\u003Cem\u003ENo\u003C\/em\u003E \u003Cem\u003EImages\u003C\/em\u003E \u003Cem\u003EProduced\u003C\/em\u003E\nEFTA00033209"]}},{"_source":{"documentId":"0f0c9cf2","chunkIndex":0,"totalChunks":1,"charStart":0,"charEnd":31,"chunkSize":31,"isChunked":false,"startPage":1,"endPage":1,"ORIGIN_FILE_NAME":"EFTA00033007.pdf","ORIGIN_FILE_URI":"https:\/\/www.justice.gov\/epstein\/files\/DataSet 8\/EFTA00033007.pdf","bucket":"amazon-s3x-sync","key":"DataSet 8\/EFTA00033007.pdf","contentType":"application\/pdf","fileSize":2433,"totalWords":4,"totalCharacters":31,"processedAt":"2026-01-21T01:39:27Z","indexedAt":"2026-01-21T01:39:27Z","source":"document-indexing-pipeline"},"fields":{"ORIGIN_FILE_NAME":["EFTA00033007.pdf"]},"highlight":{"content":["\u003Cem\u003ENo\u003C\/em\u003E \u003Cem\u003EImages\u003C\/em\u003E \u003Cem\u003EProduced\u003C\/em\u003E\nEFTA00033007"]}},{"_source":{"documentId":"ace5ddd7","chunkIndex":0,"totalChunks":1,"charStart":0,"charEnd":31,"chunkSize":31,"isChunked":false,"startPage":1,"endPage":1,"ORIGIN_FILE_NAME":"EFTA00033161.pdf","ORIGIN_FILE_URI":"https:\/\/www.justice.gov\/epstein\/files\/DataSet 8\/EFTA00033161.pdf","bucket":"amazon-s3x-sync","key":"DataSet 8\/EFTA00033161.pdf","contentType":"application\/pdf","fileSize":2433,"totalWords":4,"totalCharacters":31,"processedAt":"2026-01-21T01:39:27Z","indexedAt":"2026-01-21T01:39:27Z","source":"document-indexing-pipeline"},"fields":{"ORIGIN_FILE_NAME":["EFTA00033161.pdf"]},"highlight":{"content":["\u003Cem\u003ENo\u003C\/em\u003E \u003Cem\u003EImages\u003C\/em\u003E \u003Cem\u003EProduced\u003C\/em\u003E\nEFTA00033161"]}},{"_source":{"documentId":"f966f6f6","chunkIndex":0,"totalChunks":1,"charStart":0,"charEnd":31,"chunkSize":31,"isChunked":false,"startPage":1,"endPage":1,"ORIGIN_FILE_NAME":"EFTA00033122.pdf","ORIGIN_FILE_URI":"https:\/\/www.justice.gov\/epstein\/files\/DataSet 8\/EFTA00033122.pdf","bucket":"amazon-s3x-sync","key":"DataSet 8\/EFTA00033122.pdf","contentType":"application\/pdf","fileSize":2433,"totalWords":4,"totalCharacters":31,"processedAt":"2026-01-21T01:39:27Z","indexedAt":"2026-01-21T01:39:27Z","source":"document-indexing-pipeline"},"fields":{"ORIGIN_FILE_NAME":["EFTA00033122.pdf"]},"highlight":{"content":["\u003Cem\u003ENo\u003C\/em\u003E \u003Cem\u003EImages\u003C\/em\u003E \u003Cem\u003EProduced\u003C\/em\u003E\nEFTA00033122"]}},{"_source":{"documentId":"3846e2b0","chunkIndex":0,"totalChunks":1,"charStart":0,"charEnd":31,"chunkSize":31,"isChunked":false,"startPage":1,"endPage":1,"ORIGIN_FILE_NAME":"EFTA00033285.pdf","ORIGIN_FILE_URI":"https:\/\/www.justice.gov\/epstein\/files\/DataSet 8\/EFTA00033285.pdf","bucket":"amazon-s3x-sync","key":"DataSet 8\/EFTA00033285.pdf","contentType":"application\/pdf","fileSize":2433,"totalWords":4,"totalCharacters":31,"processedAt":"2026-01-21T01:39:28Z","indexedAt":"2026-01-21T01:39:28Z","source":"document-indexing-pipeline"},"fields":{"ORIGIN_FILE_NAME":["EFTA00033285.pdf"]},"highlight":{"content":["\u003Cem\u003ENo\u003C\/em\u003E \u003Cem\u003EImages\u003C\/em\u003E \u003Cem\u003EProduced\u003C\/em\u003E\nEFTA00033285"]}}]},"aggregations":{"unique_count":{"value":3803}}}